uif_client/__init__.py
uif_client/__main__.py
uif_client/main.py
abc_0329_linux-1627139781.dist-info/METADATA
abc_0329_linux-1627139781.dist-info/WHEEL
abc_0329_linux-1627139781.dist-info/top_level.txt
abc_0329_linux-1627139781.dist-info/RECORD
