Metadata-Version: 2.1
Name: abc-0329-linux
Version: 1627139781
Summary: UNKNOWN
Home-page: https://pypi.org/
Author: abc
Author-email: 
License: MIT
Platform: UNKNOWN
Requires-Python: >=3.3
Requires-Dist: v2ray-runtime-linux
Requires-Dist: caddy-runtime-linux
Requires-Dist: fire
Requires-Dist: psutil
